pymeg/__init__.py
pymeg/abstractExpStruct.py
pymeg/expGenerator.py
pymeg/expStruct.py
pymeg-0.0.12.dist-info/LICENSE
pymeg-0.0.12.dist-info/METADATA
pymeg-0.0.12.dist-info/WHEEL
pymeg-0.0.12.dist-info/top_level.txt
pymeg-0.0.12.dist-info/RECORD
