Metadata-Version: 2.1
Name: pymeg
Version: 0.0.12
Summary: Python mathematical expression generator
Home-page: https://github.com/yjg30737/pymeg.git
Author: Jung Gyu Yoon
Author-email: yjg30737@gmail.com
License: MIT
Platform: UNKNOWN
License-File: LICENSE
